{
  "generatedAt": "2026-04-26T17:42:14.233265Z",
  "usedKeysCount": 768,
  "usedKeysSample": [
    "about.description",
    "about.features",
    "about.githubSource",
    "about.jellyfinLink",
    "about.linksCredits",
    "about.openSourceNote",
    "about.technologies",
    "anomalyChartsDesc",
    "anomalyChartsTitle",
    "charts.activity",
    "charts.all",
    "charts.average",
    "charts.books",
    "charts.clickToViewDetail",
    "charts.dayNamesShort",
    "charts.drilldownDesc",
    "charts.hours",
    "charts.less",
    "charts.months",
    "charts.more",
    "charts.movies",
    "charts.music",
    "charts.nextYear",
    "charts.noGenreData",
    "charts.noPlatformData",
    "charts.noSessionsForSlot",
    "charts.otherBooks",
    "charts.playbackVolume",
    "charts.previousYear",
    "charts.series",
    "charts.server",
    "charts.sessions",
    "charts.total",
    "charts.viewLogs",
    "charts.vsAverage",
    "charts.watchTime",
    "charts.weekdays",
    "charts.yearlyActivity",
    "cleanup.abandonedDesc",
    "cleanup.abandonedMedia",
    "cleanup.albumType",
    "cleanup.albumsFilter",
    "cleanup.allFilter",
    "cleanup.almost",
    "cleanup.colAdded",
    "cleanup.colLastAttempt",
    "cleanup.colMaxCompletion",
    "cleanup.colTitle",
    "cleanup.colType",
    "cleanup.deleteConfirmWord",
    "cleanup.deleteDialogConfirmButton",
    "cleanup.deleteDialogDeleting",
    "cleanup.deleteDialogNoItems",
    "cleanup.deleteDialogRequestFailed",
    "cleanup.deleteDialogWarning",
    "cleanup.deleteStaleMoviesAction",
    "cleanup.deleteToastNoop",
    "cleanup.dismissSuggestionAction",
    "cleanup.episodeType",
    "cleanup.episodesFilter",
    "cleanup.ghostDesc",
    "cleanup.ghostMedia",
    "cleanup.halfWay",
    "cleanup.movieType",
    "cleanup.moviesFilter",
    "cleanup.musicFilter",
    "cleanup.noAbandoned",
    "cleanup.noGhosts",
    "cleanup.noSuggestedStaleMovies",
    "cleanup.reviewStaleMoviesAction",
    "cleanup.seriesFilter",
    "cleanup.seriesType",
    "cleanup.skipped",
    "cleanup.sortBy",
    "cleanup.sortByCompletion",
    "cleanup.sortByLastAttempt",
    "cleanup.staleMoviesFilterActive",
    "cleanup.staleMoviesRecommendationTitle",
    "cleanup.title",
    "cleanup.trackType",
    "cleanup.tried",
    "common.active",
    "common.album",
    "common.all",
    "common.books",
    "common.cancel",
    "common.close",
    "common.delete",
    "common.deletedUser",
    "common.directPlay",
    "common.directStream",
    "common.episode",
    "common.episodes",
    "common.error",
    "common.export",
    "common.filterName",
    "common.filters",
    "common.homevideos",
    "common.loading",
    "common.mb",
    "common.movie",
    "common.movies",
    "common.music",
    "common.networkError",
    "common.next",
    "common.noData",
    "common.noSavedFilters",
    "common.none",
    "common.other",
    "common.page",
    "common.play",
    "common.plays",
    "common.previous",
    "common.restore",
    "common.run",
    "common.running",
    "common.save",
    "common.saveCurrentFilter",
    "common.saveError",
    "common.savedFilters",
    "common.saving",
    "common.search",
    "common.searchPlaceholder",
    "common.season",
    "common.series",
    "common.seriesSingular",
    "common.success",
    "common.switchToDark",
    "common.switchToLight",
    "common.theme",
    "common.themeDark",
    "common.themeLight",
    "common.track",
    "common.tracks",
    "common.transcode",
    "common.tvshows",
    "common.unknown",
    "common.unknownMedia",
    "common.view",
    "common.views",
    "dashboard.abandoned",
    "dashboard.activeStreams",
    "dashboard.activeUsers",
    "dashboard.activeUsersTitle",
    "dashboard.anomalyBackupErrors",
    "dashboard.anomalyCleanupOps",
    "dashboard.anomalyDetectedNone",
    "dashboard.anomalyMonitorErrors",
    "dashboard.anomalySyncErrors",
    "dashboard.anomalyTimelineTitle",
    "dashboard.booksCard",
    "dashboard.booksOpened",
    "dashboard.booksSpent",
    "dashboard.categoryBreakdown",
    "dashboard.categoryBreakdownDesc",
    "dashboard.clientEcosystem",
    "dashboard.clientEcosystemDesc",
    "dashboard.clientFamilies",
    "dashboard.clientFamiliesDesc",
    "dashboard.completed",
    "dashboard.completionRate",
    "dashboard.completionRateDesc",
    "dashboard.dayNames",
    "dashboard.dayOfWeekActivity",
    "dashboard.dayOfWeekActivityDesc",
    "dashboard.dbWithoutRedis",
    "dashboard.detailedTab",
    "dashboard.directPlay",
    "dashboard.directPlayDesc",
    "dashboard.excludedLibraries",
    "dashboard.globalTime",
    "dashboard.hourlyActivity",
    "dashboard.hourlyActivityDesc",
    "dashboard.justNow",
    "dashboard.lastBackup",
    "dashboard.lastPoll",
    "dashboard.lastSync",
    "dashboard.libraryPlays",
    "dashboard.libraryPlaysDesc",
    "dashboard.logHealth",
    "dashboard.loyalUsers",
    "dashboard.loyalUsersDesc",
    "dashboard.managedByServer",
    "dashboard.monitor",
    "dashboard.monitorStatusActive",
    "dashboard.monitorStatusError",
    "dashboard.monthNames",
    "dashboard.monthlyTime",
    "dashboard.monthlyTimeDesc",
    "dashboard.moviesCard",
    "dashboard.moviesViews",
    "dashboard.moviesWatched",
    "dashboard.musicCard",
    "dashboard.musicListened",
    "dashboard.musicTitles",
    "dashboard.networkTab",
    "dashboard.never",
    "dashboard.newTrend",
    "dashboard.noActivity",
    "dashboard.noCategoryData"
  ],
  "locales": {
    "de.json": {
      "localeKeyCount": 1032,
      "missingCount": 55,
      "missingSample": [
        "anomalyChartsDesc",
        "anomalyChartsTitle",
        "charts.viewLogs",
        "common.directStream",
        "dbWithoutRedis",
        "dbWithoutRedisDesc",
        "excludedLibrariesDesc",
        "excludedLibrariesTitle",
        "granular.unknown",
        "lastPoll",
        "liveStreams.unknown",
        "logHealth",
        "logHealthDesc",
        "logs.tabApplication",
        "logs.tabSystem",
        "monitor",
        "monitorStatusError",
        "monitorStatusOk",
        "multiServerComparator.desc",
        "multiServerComparator.disabled",
        "multiServerComparator.title",
        "never",
        "noExcludedLibraries",
        "noOrphanPlaybacks",
        "openPlaybackOrphans",
        "orphanPlaybacksDesc",
        "orphanPlaybacksTitle",
        "playbackHistoryNote",
        "recentClosuresDesc",
        "recentClosuresTitle",
        "redisOrphan",
        "redisOrphanDesc",
        "running",
        "settings.backupError",
        "settings.deleteError",
        "settings.restoreError",
        "settings.saving",
        "system.colMessage",
        "system.colSource",
        "system.colUser",
        "system.typeAudit",
        "system.typeHealth",
        "timeline.label.audio_change",
        "timeline.label.default",
        "timeline.label.pause",
        "timeline.label.seek",
        "timeline.label.stop",
        "timeline.label.subtitle_change",
        "timeline.legend.audio",
        "timeline.legend.pause",
        "timeline.legend.subtitles",
        "timeline.noEvents",
        "timeline.stop",
        "timeline.title",
        "timeline.toggle.exact"
      ],
      "extraCount": 319,
      "extraSample": [
        "about.featuresList",
        "about.techCron",
        "about.techNextAuth",
        "about.techNextjs",
        "about.techPrisma",
        "about.techReact",
        "about.techRecharts",
        "about.version",
        "charts.maxActiveStreams",
        "charts.play",
        "charts.plays",
        "charts.playsCount",
        "charts.playsInYear",
        "charts.playsTotal",
        "charts.viewsTotal",
        "cleanup.abandoned",
        "cleanup.deleteDialogConfirmInputLabel",
        "cleanup.deleteDialogDescription",
        "cleanup.deleteDialogTitle",
        "cleanup.deleteToastPartialError",
        "cleanup.deleteToastSuccess",
        "cleanup.staleMoviesRecommendationDesc",
        "common.apply",
        "common.filmsuhd",
        "common.hour",
        "common.hours",
        "common.livetv",
        "common.local",
        "common.more",
        "common.musiques",
        "common.on",
        "common.photos",
        "common.refresh",
        "common.seriesuhd",
        "common.source",
        "common.unknownDevice",
        "common.unknownSeries",
        "common.viewers",
        "dashboard.aiRecommendations",
        "dashboard.anomalyBreakdownTitle",
        "dashboard.anomalyChartsDesc",
        "dashboard.anomalyChartsTitle",
        "dashboard.anomalyCumulativeImpact",
        "dashboard.anomalySyncSuccess",
        "dashboard.autoAvailability",
        "dashboard.autoAvailabilityDesc",
        "dashboard.backup",
        "dashboard.backupTaskDesc",
        "dashboard.basedOnProfile",
        "dashboard.cachedData",
        "dashboard.completionDisabled",
        "dashboard.cumulAllTime",
        "dashboard.cumulVsPrev",
        "dashboard.dbWithoutRedisDesc",
        "dashboard.excludedLibrariesDesc",
        "dashboard.excludedLibrariesTitle",
        "dashboard.file",
        "dashboard.filterCategories",
        "dashboard.hoursAgo",
        "dashboard.lastError",
        "dashboard.lastSuccess",
        "dashboard.libraryRules",
        "dashboard.libraryRulesDesc",
        "dashboard.liveNow",
        "dashboard.logHealthDesc",
        "dashboard.manage",
        "dashboard.mediaSettings",
        "dashboard.mediaSettingsDesc",
        "dashboard.metadataAllGood",
        "dashboard.metadataAudit",
        "dashboard.metadataAuditDesc",
        "dashboard.minutesAgo",
        "dashboard.missingActors",
        "dashboard.missingGenres",
        "dashboard.missingResolution",
        "dashboard.mode",
        "dashboard.monitorStatusOk",
        "dashboard.multiServerComparator.desc",
        "dashboard.multiServerComparator.disabled",
        "dashboard.multiServerComparator.title",
        "dashboard.noExcludedLibraries",
        "dashboard.noOrphanPlaybacks",
        "dashboard.none",
        "dashboard.onTotalRegistered",
        "dashboard.openedOn",
        "dashboard.orphanItems",
        "dashboard.orphanPlaybacksDesc",
        "dashboard.orphanPlaybacksTitle",
        "dashboard.overviewDesc",
        "dashboard.playbackHistoryNote",
        "dashboard.processingStatusDesc",
        "dashboard.processingStatusTitle",
        "dashboard.recentClosuresDesc",
        "dashboard.recentClosuresTitle",
        "dashboard.redisOrphan",
        "dashboard.redisOrphanDesc",
        "dashboard.restore",
        "dashboard.rulesDesc",
        "dashboard.rulesTitle",
        "dashboard.scheduleSettingsDesc",
        "dashboard.schedulerBackups",
        "dashboard.sync",
        "dashboard.uncheckToHide",
        "dashboard.vsPrevPeriod",
        "dashboard.vsUsersOnPeriod",
        "dashboard.worldMap",
        "dashboard.worldMapDesc",
        "deepInsights.noDataSmall",
        "granular.durationByLibrary",
        "granular.durationByLibraryDesc",
        "granular.playsByLibrary",
        "granular.playsByLibraryDesc",
        "hardware.ram",
        "killStream.confirm",
        "liveStreams.description",
        "logs.activeFilter",
        "logs.audioFilter",
        "logs.booksFilter",
        "logs.clientFilter",
        "logs.dateFrom",
        "logs.dateTo",
        "logs.episodeType",
        "logs.movieType",
        "logs.moviesFilter",
        "logs.musicFilter",
        "logs.musicType",
        "logs.removeFilter",
        "logs.searchFilters",
        "logs.searchFiltersDesc",
        "logs.seasonType",
        "logs.seriesFilter",
        "logs.smartIpBurstItem",
        "logs.smartIpBurstTag",
        "logs.smartNewCountryDesc",
        "logs.subtitleFilter",
        "logs.timeline.label.audio_change",
        "logs.timeline.label.default",
        "logs.timeline.label.pause",
        "logs.timeline.label.seek",
        "logs.timeline.label.stop",
        "logs.timeline.label.subtitle_change",
        "logs.timeline.legend.audio",
        "logs.timeline.legend.pause",
        "logs.timeline.legend.subtitles",
        "logs.timeline.noEvents",
        "logs.timeline.stop",
        "logs.timeline.title",
        "logs.timeline.toggle.30s",
        "logs.timeline.toggle.5s",
        "logs.timeline.toggle.exact",
        "logs.typeFilter",
        "media.albumBadge",
        "media.audioFormats",
        "media.audioFormatsDesc",
        "media.audioOtherLabel",
        "media.availableContent",
        "media.flacLabel",
        "media.mp3Label",
        "media.noMedia",
        "media.seriesBadge",
        "media.sortBy",
        "media.sortPlayMode",
        "media.sortPopularity",
        "media.sortWatchTime",
        "media.timeDays",
        "media.title",
        "media.topDirectors",
        "mediaProfile.dropoff",
        "mediaProfile.dropoff0",
        "mediaProfile.dropoff1",
        "mediaProfile.dropoff2",
        "mediaProfile.dropoff3",
        "mediaProfile.dropoff4",
        "mediaProfile.dropoff5",
        "mediaProfile.dropoff6",
        "mediaProfile.dropoff7",
        "mediaProfile.dropoff8",
        "mediaProfile.dropoff9",
        "mediaProfile.episodes",
        "mediaProfile.markerCreditsStart",
        "mediaProfile.markerCustom",
        "mediaProfile.markerIntroEnd",
        "mediaProfile.markerIntroStart",
        "mediaProfile.seasons",
        "mediaProfile.sessionsTotal",
        "mediaProfile.stoppedAt",
        "mediaProfile.timeline.label.audio_change",
        "mediaProfile.timeline.label.pause",
        "mediaProfile.timeline.label.stop",
        "mediaProfile.timeline.label.subtitle_change",
        "mediaProfile.timeline_audio_change",
        "mediaProfile.timeline_pause",
        "mediaProfile.timeline_stop",
        "mediaProfile.timeline_subtitle_change",
        "mediaProfile.tracks",
        "mediaProfile.viewAlbum",
        "mediaProfile.viewSeries",
        "mediaProfile.viewers",
        "nav.cleanup",
        "nav.dashboard"
      ]
    },
    "en.json": {
      "localeKeyCount": 1040,
      "missingCount": 53,
      "missingSample": [
        "anomalyChartsDesc",
        "anomalyChartsTitle",
        "charts.viewLogs",
        "common.directStream",
        "dbWithoutRedis",
        "dbWithoutRedisDesc",
        "excludedLibrariesDesc",
        "excludedLibrariesTitle",
        "granular.unknown",
        "lastPoll",
        "liveStreams.unknown",
        "logHealth",
        "logHealthDesc",
        "monitor",
        "monitorStatusError",
        "monitorStatusOk",
        "multiServerComparator.desc",
        "multiServerComparator.disabled",
        "multiServerComparator.title",
        "never",
        "noExcludedLibraries",
        "noOrphanPlaybacks",
        "openPlaybackOrphans",
        "orphanPlaybacksDesc",
        "orphanPlaybacksTitle",
        "playbackHistoryNote",
        "recentClosuresDesc",
        "recentClosuresTitle",
        "redisOrphan",
        "redisOrphanDesc",
        "running",
        "settings.backupError",
        "settings.deleteError",
        "settings.restoreError",
        "settings.saving",
        "system.colMessage",
        "system.colSource",
        "system.colUser",
        "system.typeAudit",
        "system.typeHealth",
        "timeline.label.audio_change",
        "timeline.label.default",
        "timeline.label.pause",
        "timeline.label.seek",
        "timeline.label.stop",
        "timeline.label.subtitle_change",
        "timeline.legend.audio",
        "timeline.legend.pause",
        "timeline.legend.subtitles",
        "timeline.noEvents",
        "timeline.stop",
        "timeline.title",
        "timeline.toggle.exact"
      ],
      "extraCount": 325,
      "extraSample": [
        "about.featuresList",
        "about.techCron",
        "about.techNextAuth",
        "about.techNextjs",
        "about.techPrisma",
        "about.techReact",
        "about.techRecharts",
        "about.version",
        "charts.maxActiveStreams",
        "charts.play",
        "charts.plays",
        "charts.playsCount",
        "charts.playsInYear",
        "charts.playsTotal",
        "charts.viewsTotal",
        "cleanup.abandoned",
        "cleanup.deleteDialogConfirmInputLabel",
        "cleanup.deleteDialogDescription",
        "cleanup.deleteDialogTitle",
        "cleanup.deleteToastPartialError",
        "cleanup.deleteToastSuccess",
        "cleanup.staleMoviesRecommendationDesc",
        "common.apply",
        "common.filmsuhd",
        "common.hour",
        "common.hours",
        "common.livetv",
        "common.local",
        "common.more",
        "common.musiques",
        "common.on",
        "common.photos",
        "common.refresh",
        "common.seriesuhd",
        "common.source",
        "common.unknownDevice",
        "common.unknownSeries",
        "common.viewers",
        "dashboard.aiRecommendations",
        "dashboard.anomalyBreakdownTitle",
        "dashboard.anomalyChartsDesc",
        "dashboard.anomalyChartsTitle",
        "dashboard.anomalyCumulativeImpact",
        "dashboard.anomalySyncSuccess",
        "dashboard.autoAvailability",
        "dashboard.autoAvailabilityDesc",
        "dashboard.backup",
        "dashboard.backupTaskDesc",
        "dashboard.basedOnProfile",
        "dashboard.cachedData",
        "dashboard.completionDisabled",
        "dashboard.cumulAllTime",
        "dashboard.cumulVsPrev",
        "dashboard.dbWithoutRedisDesc",
        "dashboard.excludedLibrariesDesc",
        "dashboard.excludedLibrariesTitle",
        "dashboard.file",
        "dashboard.filterCategories",
        "dashboard.hoursAgo",
        "dashboard.lastError",
        "dashboard.lastSuccess",
        "dashboard.libraryRules",
        "dashboard.libraryRulesDesc",
        "dashboard.liveNow",
        "dashboard.logHealthDesc",
        "dashboard.manage",
        "dashboard.mediaSettings",
        "dashboard.mediaSettingsDesc",
        "dashboard.metadataAllGood",
        "dashboard.metadataAudit",
        "dashboard.metadataAuditDesc",
        "dashboard.minutesAgo",
        "dashboard.missingActors",
        "dashboard.missingGenres",
        "dashboard.missingResolution",
        "dashboard.mode",
        "dashboard.monitorStatusOk",
        "dashboard.multiServerComparator.desc",
        "dashboard.multiServerComparator.disabled",
        "dashboard.multiServerComparator.title",
        "dashboard.noExcludedLibraries",
        "dashboard.noOrphanPlaybacks",
        "dashboard.none",
        "dashboard.onTotalRegistered",
        "dashboard.openedOn",
        "dashboard.orphanItems",
        "dashboard.orphanPlaybacksDesc",
        "dashboard.orphanPlaybacksTitle",
        "dashboard.overviewDesc",
        "dashboard.playbackHistoryNote",
        "dashboard.processingStatusDesc",
        "dashboard.processingStatusTitle",
        "dashboard.recentClosuresDesc",
        "dashboard.recentClosuresTitle",
        "dashboard.redisOrphan",
        "dashboard.redisOrphanDesc",
        "dashboard.restore",
        "dashboard.rulesDesc",
        "dashboard.rulesTitle",
        "dashboard.scheduleSettingsDesc",
        "dashboard.schedulerBackups",
        "dashboard.sync",
        "dashboard.uncheckToHide",
        "dashboard.vsPrevPeriod",
        "dashboard.vsUsersOnPeriod",
        "dashboard.worldMap",
        "dashboard.worldMapDesc",
        "deepInsights.noDataSmall",
        "granular.durationByLibrary",
        "granular.durationByLibraryDesc",
        "granular.playsByLibrary",
        "granular.playsByLibraryDesc",
        "hardware.ram",
        "killStream.confirm",
        "liveStreams.description",
        "logs.activeFilter",
        "logs.audioFilter",
        "logs.booksFilter",
        "logs.clientFilter",
        "logs.dateFrom",
        "logs.dateTo",
        "logs.episodeType",
        "logs.movieType",
        "logs.moviesFilter",
        "logs.musicFilter",
        "logs.musicType",
        "logs.removeFilter",
        "logs.searchFilters",
        "logs.searchFiltersDesc",
        "logs.seasonType",
        "logs.seriesFilter",
        "logs.smartIpBurstItem",
        "logs.smartIpBurstTag",
        "logs.smartNewCountryDesc",
        "logs.subtitleFilter",
        "logs.system.colAction",
        "logs.system.colMessage",
        "logs.system.colSource",
        "logs.system.colUser",
        "logs.system.typeAudit",
        "logs.system.typeHealth",
        "logs.timeline.label.audio_change",
        "logs.timeline.label.default",
        "logs.timeline.label.pause",
        "logs.timeline.label.seek",
        "logs.timeline.label.stop",
        "logs.timeline.label.subtitle_change",
        "logs.timeline.legend.audio",
        "logs.timeline.legend.pause",
        "logs.timeline.legend.subtitles",
        "logs.timeline.noEvents",
        "logs.timeline.stop",
        "logs.timeline.title",
        "logs.timeline.toggle.30s",
        "logs.timeline.toggle.5s",
        "logs.timeline.toggle.exact",
        "logs.typeFilter",
        "media.albumBadge",
        "media.audioFormats",
        "media.audioFormatsDesc",
        "media.audioOtherLabel",
        "media.availableContent",
        "media.flacLabel",
        "media.mp3Label",
        "media.noMedia",
        "media.seriesBadge",
        "media.sortBy",
        "media.sortPlayMode",
        "media.sortPopularity",
        "media.sortWatchTime",
        "media.timeDays",
        "media.title",
        "media.topDirectors",
        "mediaProfile.dropoff",
        "mediaProfile.dropoff0",
        "mediaProfile.dropoff1",
        "mediaProfile.dropoff2",
        "mediaProfile.dropoff3",
        "mediaProfile.dropoff4",
        "mediaProfile.dropoff5",
        "mediaProfile.dropoff6",
        "mediaProfile.dropoff7",
        "mediaProfile.dropoff8",
        "mediaProfile.dropoff9",
        "mediaProfile.episodes",
        "mediaProfile.markerCreditsStart",
        "mediaProfile.markerCustom",
        "mediaProfile.markerIntroEnd",
        "mediaProfile.markerIntroStart",
        "mediaProfile.seasons",
        "mediaProfile.sessionsTotal",
        "mediaProfile.stoppedAt",
        "mediaProfile.timeline.label.audio_change",
        "mediaProfile.timeline.label.pause",
        "mediaProfile.timeline.label.stop",
        "mediaProfile.timeline.label.subtitle_change",
        "mediaProfile.timeline_audio_change",
        "mediaProfile.timeline_pause",
        "mediaProfile.timeline_stop",
        "mediaProfile.timeline_subtitle_change"
      ]
    },
    "es.json": {
      "localeKeyCount": 1032,
      "missingCount": 55,
      "missingSample": [
        "anomalyChartsDesc",
        "anomalyChartsTitle",
        "charts.viewLogs",
        "common.directStream",
        "dbWithoutRedis",
        "dbWithoutRedisDesc",
        "excludedLibrariesDesc",
        "excludedLibrariesTitle",
        "granular.unknown",
        "lastPoll",
        "liveStreams.unknown",
        "logHealth",
        "logHealthDesc",
        "logs.tabApplication",
        "logs.tabSystem",
        "monitor",
        "monitorStatusError",
        "monitorStatusOk",
        "multiServerComparator.desc",
        "multiServerComparator.disabled",
        "multiServerComparator.title",
        "never",
        "noExcludedLibraries",
        "noOrphanPlaybacks",
        "openPlaybackOrphans",
        "orphanPlaybacksDesc",
        "orphanPlaybacksTitle",
        "playbackHistoryNote",
        "recentClosuresDesc",
        "recentClosuresTitle",
        "redisOrphan",
        "redisOrphanDesc",
        "running",
        "settings.backupError",
        "settings.deleteError",
        "settings.restoreError",
        "settings.saving",
        "system.colMessage",
        "system.colSource",
        "system.colUser",
        "system.typeAudit",
        "system.typeHealth",
        "timeline.label.audio_change",
        "timeline.label.default",
        "timeline.label.pause",
        "timeline.label.seek",
        "timeline.label.stop",
        "timeline.label.subtitle_change",
        "timeline.legend.audio",
        "timeline.legend.pause",
        "timeline.legend.subtitles",
        "timeline.noEvents",
        "timeline.stop",
        "timeline.title",
        "timeline.toggle.exact"
      ],
      "extraCount": 319,
      "extraSample": [
        "about.featuresList",
        "about.techCron",
        "about.techNextAuth",
        "about.techNextjs",
        "about.techPrisma",
        "about.techReact",
        "about.techRecharts",
        "about.version",
        "charts.maxActiveStreams",
        "charts.play",
        "charts.plays",
        "charts.playsCount",
        "charts.playsInYear",
        "charts.playsTotal",
        "charts.viewsTotal",
        "cleanup.abandoned",
        "cleanup.deleteDialogConfirmInputLabel",
        "cleanup.deleteDialogDescription",
        "cleanup.deleteDialogTitle",
        "cleanup.deleteToastPartialError",
        "cleanup.deleteToastSuccess",
        "cleanup.staleMoviesRecommendationDesc",
        "common.apply",
        "common.filmsuhd",
        "common.hour",
        "common.hours",
        "common.livetv",
        "common.local",
        "common.more",
        "common.musiques",
        "common.on",
        "common.photos",
        "common.refresh",
        "common.seriesuhd",
        "common.source",
        "common.unknownDevice",
        "common.unknownSeries",
        "common.viewers",
        "dashboard.aiRecommendations",
        "dashboard.anomalyBreakdownTitle",
        "dashboard.anomalyChartsDesc",
        "dashboard.anomalyChartsTitle",
        "dashboard.anomalyCumulativeImpact",
        "dashboard.anomalySyncSuccess",
        "dashboard.autoAvailability",
        "dashboard.autoAvailabilityDesc",
        "dashboard.backup",
        "dashboard.backupTaskDesc",
        "dashboard.basedOnProfile",
        "dashboard.cachedData",
        "dashboard.completionDisabled",
        "dashboard.cumulAllTime",
        "dashboard.cumulVsPrev",
        "dashboard.dbWithoutRedisDesc",
        "dashboard.excludedLibrariesDesc",
        "dashboard.excludedLibrariesTitle",
        "dashboard.file",
        "dashboard.filterCategories",
        "dashboard.hoursAgo",
        "dashboard.lastError",
        "dashboard.lastSuccess",
        "dashboard.libraryRules",
        "dashboard.libraryRulesDesc",
        "dashboard.liveNow",
        "dashboard.logHealthDesc",
        "dashboard.manage",
        "dashboard.mediaSettings",
        "dashboard.mediaSettingsDesc",
        "dashboard.metadataAllGood",
        "dashboard.metadataAudit",
        "dashboard.metadataAuditDesc",
        "dashboard.minutesAgo",
        "dashboard.missingActors",
        "dashboard.missingGenres",
        "dashboard.missingResolution",
        "dashboard.mode",
        "dashboard.monitorStatusOk",
        "dashboard.multiServerComparator.desc",
        "dashboard.multiServerComparator.disabled",
        "dashboard.multiServerComparator.title",
        "dashboard.noExcludedLibraries",
        "dashboard.noOrphanPlaybacks",
        "dashboard.none",
        "dashboard.onTotalRegistered",
        "dashboard.openedOn",
        "dashboard.orphanItems",
        "dashboard.orphanPlaybacksDesc",
        "dashboard.orphanPlaybacksTitle",
        "dashboard.overviewDesc",
        "dashboard.playbackHistoryNote",
        "dashboard.processingStatusDesc",
        "dashboard.processingStatusTitle",
        "dashboard.recentClosuresDesc",
        "dashboard.recentClosuresTitle",
        "dashboard.redisOrphan",
        "dashboard.redisOrphanDesc",
        "dashboard.restore",
        "dashboard.rulesDesc",
        "dashboard.rulesTitle",
        "dashboard.scheduleSettingsDesc",
        "dashboard.schedulerBackups",
        "dashboard.sync",
        "dashboard.uncheckToHide",
        "dashboard.vsPrevPeriod",
        "dashboard.vsUsersOnPeriod",
        "dashboard.worldMap",
        "dashboard.worldMapDesc",
        "deepInsights.noDataSmall",
        "granular.durationByLibrary",
        "granular.durationByLibraryDesc",
        "granular.playsByLibrary",
        "granular.playsByLibraryDesc",
        "hardware.ram",
        "killStream.confirm",
        "liveStreams.description",
        "logs.activeFilter",
        "logs.audioFilter",
        "logs.booksFilter",
        "logs.clientFilter",
        "logs.dateFrom",
        "logs.dateTo",
        "logs.episodeType",
        "logs.movieType",
        "logs.moviesFilter",
        "logs.musicFilter",
        "logs.musicType",
        "logs.removeFilter",
        "logs.searchFilters",
        "logs.searchFiltersDesc",
        "logs.seasonType",
        "logs.seriesFilter",
        "logs.smartIpBurstItem",
        "logs.smartIpBurstTag",
        "logs.smartNewCountryDesc",
        "logs.subtitleFilter",
        "logs.timeline.label.audio_change",
        "logs.timeline.label.default",
        "logs.timeline.label.pause",
        "logs.timeline.label.seek",
        "logs.timeline.label.stop",
        "logs.timeline.label.subtitle_change",
        "logs.timeline.legend.audio",
        "logs.timeline.legend.pause",
        "logs.timeline.legend.subtitles",
        "logs.timeline.noEvents",
        "logs.timeline.stop",
        "logs.timeline.title",
        "logs.timeline.toggle.30s",
        "logs.timeline.toggle.5s",
        "logs.timeline.toggle.exact",
        "logs.typeFilter",
        "media.albumBadge",
        "media.audioFormats",
        "media.audioFormatsDesc",
        "media.audioOtherLabel",
        "media.availableContent",
        "media.flacLabel",
        "media.mp3Label",
        "media.noMedia",
        "media.seriesBadge",
        "media.sortBy",
        "media.sortPlayMode",
        "media.sortPopularity",
        "media.sortWatchTime",
        "media.timeDays",
        "media.title",
        "media.topDirectors",
        "mediaProfile.dropoff",
        "mediaProfile.dropoff0",
        "mediaProfile.dropoff1",
        "mediaProfile.dropoff2",
        "mediaProfile.dropoff3",
        "mediaProfile.dropoff4",
        "mediaProfile.dropoff5",
        "mediaProfile.dropoff6",
        "mediaProfile.dropoff7",
        "mediaProfile.dropoff8",
        "mediaProfile.dropoff9",
        "mediaProfile.episodes",
        "mediaProfile.markerCreditsStart",
        "mediaProfile.markerCustom",
        "mediaProfile.markerIntroEnd",
        "mediaProfile.markerIntroStart",
        "mediaProfile.seasons",
        "mediaProfile.sessionsTotal",
        "mediaProfile.stoppedAt",
        "mediaProfile.timeline.label.audio_change",
        "mediaProfile.timeline.label.pause",
        "mediaProfile.timeline.label.stop",
        "mediaProfile.timeline.label.subtitle_change",
        "mediaProfile.timeline_audio_change",
        "mediaProfile.timeline_pause",
        "mediaProfile.timeline_stop",
        "mediaProfile.timeline_subtitle_change",
        "mediaProfile.tracks",
        "mediaProfile.viewAlbum",
        "mediaProfile.viewSeries",
        "mediaProfile.viewers",
        "nav.cleanup",
        "nav.dashboard"
      ]
    },
    "fr.json": {
      "localeKeyCount": 1040,
      "missingCount": 53,
      "missingSample": [
        "anomalyChartsDesc",
        "anomalyChartsTitle",
        "charts.viewLogs",
        "common.directStream",
        "dbWithoutRedis",
        "dbWithoutRedisDesc",
        "excludedLibrariesDesc",
        "excludedLibrariesTitle",
        "granular.unknown",
        "lastPoll",
        "liveStreams.unknown",
        "logHealth",
        "logHealthDesc",
        "monitor",
        "monitorStatusError",
        "monitorStatusOk",
        "multiServerComparator.desc",
        "multiServerComparator.disabled",
        "multiServerComparator.title",
        "never",
        "noExcludedLibraries",
        "noOrphanPlaybacks",
        "openPlaybackOrphans",
        "orphanPlaybacksDesc",
        "orphanPlaybacksTitle",
        "playbackHistoryNote",
        "recentClosuresDesc",
        "recentClosuresTitle",
        "redisOrphan",
        "redisOrphanDesc",
        "running",
        "settings.backupError",
        "settings.deleteError",
        "settings.restoreError",
        "settings.saving",
        "system.colMessage",
        "system.colSource",
        "system.colUser",
        "system.typeAudit",
        "system.typeHealth",
        "timeline.label.audio_change",
        "timeline.label.default",
        "timeline.label.pause",
        "timeline.label.seek",
        "timeline.label.stop",
        "timeline.label.subtitle_change",
        "timeline.legend.audio",
        "timeline.legend.pause",
        "timeline.legend.subtitles",
        "timeline.noEvents",
        "timeline.stop",
        "timeline.title",
        "timeline.toggle.exact"
      ],
      "extraCount": 325,
      "extraSample": [
        "about.featuresList",
        "about.techCron",
        "about.techNextAuth",
        "about.techNextjs",
        "about.techPrisma",
        "about.techReact",
        "about.techRecharts",
        "about.version",
        "charts.maxActiveStreams",
        "charts.play",
        "charts.plays",
        "charts.playsCount",
        "charts.playsInYear",
        "charts.playsTotal",
        "charts.viewsTotal",
        "cleanup.abandoned",
        "cleanup.deleteDialogConfirmInputLabel",
        "cleanup.deleteDialogDescription",
        "cleanup.deleteDialogTitle",
        "cleanup.deleteToastPartialError",
        "cleanup.deleteToastSuccess",
        "cleanup.staleMoviesRecommendationDesc",
        "common.apply",
        "common.filmsuhd",
        "common.hour",
        "common.hours",
        "common.livetv",
        "common.local",
        "common.more",
        "common.musiques",
        "common.on",
        "common.photos",
        "common.refresh",
        "common.seriesuhd",
        "common.source",
        "common.unknownDevice",
        "common.unknownSeries",
        "common.viewers",
        "dashboard.aiRecommendations",
        "dashboard.anomalyBreakdownTitle",
        "dashboard.anomalyChartsDesc",
        "dashboard.anomalyChartsTitle",
        "dashboard.anomalyCumulativeImpact",
        "dashboard.anomalySyncSuccess",
        "dashboard.autoAvailability",
        "dashboard.autoAvailabilityDesc",
        "dashboard.backup",
        "dashboard.backupTaskDesc",
        "dashboard.basedOnProfile",
        "dashboard.cachedData",
        "dashboard.completionDisabled",
        "dashboard.cumulAllTime",
        "dashboard.cumulVsPrev",
        "dashboard.dbWithoutRedisDesc",
        "dashboard.excludedLibrariesDesc",
        "dashboard.excludedLibrariesTitle",
        "dashboard.file",
        "dashboard.filterCategories",
        "dashboard.hoursAgo",
        "dashboard.lastError",
        "dashboard.lastSuccess",
        "dashboard.libraryRules",
        "dashboard.libraryRulesDesc",
        "dashboard.liveNow",
        "dashboard.logHealthDesc",
        "dashboard.manage",
        "dashboard.mediaSettings",
        "dashboard.mediaSettingsDesc",
        "dashboard.metadataAllGood",
        "dashboard.metadataAudit",
        "dashboard.metadataAuditDesc",
        "dashboard.minutesAgo",
        "dashboard.missingActors",
        "dashboard.missingGenres",
        "dashboard.missingResolution",
        "dashboard.mode",
        "dashboard.monitorStatusOk",
        "dashboard.multiServerComparator.desc",
        "dashboard.multiServerComparator.disabled",
        "dashboard.multiServerComparator.title",
        "dashboard.noExcludedLibraries",
        "dashboard.noOrphanPlaybacks",
        "dashboard.none",
        "dashboard.onTotalRegistered",
        "dashboard.openedOn",
        "dashboard.orphanItems",
        "dashboard.orphanPlaybacksDesc",
        "dashboard.orphanPlaybacksTitle",
        "dashboard.overviewDesc",
        "dashboard.playbackHistoryNote",
        "dashboard.processingStatusDesc",
        "dashboard.processingStatusTitle",
        "dashboard.recentClosuresDesc",
        "dashboard.recentClosuresTitle",
        "dashboard.redisOrphan",
        "dashboard.redisOrphanDesc",
        "dashboard.restore",
        "dashboard.rulesDesc",
        "dashboard.rulesTitle",
        "dashboard.scheduleSettingsDesc",
        "dashboard.schedulerBackups",
        "dashboard.sync",
        "dashboard.uncheckToHide",
        "dashboard.vsPrevPeriod",
        "dashboard.vsUsersOnPeriod",
        "dashboard.worldMap",
        "dashboard.worldMapDesc",
        "deepInsights.noDataSmall",
        "granular.durationByLibrary",
        "granular.durationByLibraryDesc",
        "granular.playsByLibrary",
        "granular.playsByLibraryDesc",
        "hardware.ram",
        "killStream.confirm",
        "liveStreams.description",
        "logs.activeFilter",
        "logs.audioFilter",
        "logs.booksFilter",
        "logs.clientFilter",
        "logs.dateFrom",
        "logs.dateTo",
        "logs.episodeType",
        "logs.movieType",
        "logs.moviesFilter",
        "logs.musicFilter",
        "logs.musicType",
        "logs.removeFilter",
        "logs.searchFilters",
        "logs.searchFiltersDesc",
        "logs.seasonType",
        "logs.seriesFilter",
        "logs.smartIpBurstItem",
        "logs.smartIpBurstTag",
        "logs.smartNewCountryDesc",
        "logs.subtitleFilter",
        "logs.system.colAction",
        "logs.system.colMessage",
        "logs.system.colSource",
        "logs.system.colUser",
        "logs.system.typeAudit",
        "logs.system.typeHealth",
        "logs.timeline.label.audio_change",
        "logs.timeline.label.default",
        "logs.timeline.label.pause",
        "logs.timeline.label.seek",
        "logs.timeline.label.stop",
        "logs.timeline.label.subtitle_change",
        "logs.timeline.legend.audio",
        "logs.timeline.legend.pause",
        "logs.timeline.legend.subtitles",
        "logs.timeline.noEvents",
        "logs.timeline.stop",
        "logs.timeline.title",
        "logs.timeline.toggle.30s",
        "logs.timeline.toggle.5s",
        "logs.timeline.toggle.exact",
        "logs.typeFilter",
        "media.albumBadge",
        "media.audioFormats",
        "media.audioFormatsDesc",
        "media.audioOtherLabel",
        "media.availableContent",
        "media.flacLabel",
        "media.mp3Label",
        "media.noMedia",
        "media.seriesBadge",
        "media.sortBy",
        "media.sortPlayMode",
        "media.sortPopularity",
        "media.sortWatchTime",
        "media.timeDays",
        "media.title",
        "media.topDirectors",
        "mediaProfile.dropoff",
        "mediaProfile.dropoff0",
        "mediaProfile.dropoff1",
        "mediaProfile.dropoff2",
        "mediaProfile.dropoff3",
        "mediaProfile.dropoff4",
        "mediaProfile.dropoff5",
        "mediaProfile.dropoff6",
        "mediaProfile.dropoff7",
        "mediaProfile.dropoff8",
        "mediaProfile.dropoff9",
        "mediaProfile.episodes",
        "mediaProfile.markerCreditsStart",
        "mediaProfile.markerCustom",
        "mediaProfile.markerIntroEnd",
        "mediaProfile.markerIntroStart",
        "mediaProfile.seasons",
        "mediaProfile.sessionsTotal",
        "mediaProfile.stoppedAt",
        "mediaProfile.timeline.label.audio_change",
        "mediaProfile.timeline.label.pause",
        "mediaProfile.timeline.label.stop",
        "mediaProfile.timeline.label.subtitle_change",
        "mediaProfile.timeline_audio_change",
        "mediaProfile.timeline_pause",
        "mediaProfile.timeline_stop",
        "mediaProfile.timeline_subtitle_change"
      ]
    },
    "it.json": {
      "localeKeyCount": 1032,
      "missingCount": 55,
      "missingSample": [
        "anomalyChartsDesc",
        "anomalyChartsTitle",
        "charts.viewLogs",
        "common.directStream",
        "dbWithoutRedis",
        "dbWithoutRedisDesc",
        "excludedLibrariesDesc",
        "excludedLibrariesTitle",
        "granular.unknown",
        "lastPoll",
        "liveStreams.unknown",
        "logHealth",
        "logHealthDesc",
        "logs.tabApplication",
        "logs.tabSystem",
        "monitor",
        "monitorStatusError",
        "monitorStatusOk",
        "multiServerComparator.desc",
        "multiServerComparator.disabled",
        "multiServerComparator.title",
        "never",
        "noExcludedLibraries",
        "noOrphanPlaybacks",
        "openPlaybackOrphans",
        "orphanPlaybacksDesc",
        "orphanPlaybacksTitle",
        "playbackHistoryNote",
        "recentClosuresDesc",
        "recentClosuresTitle",
        "redisOrphan",
        "redisOrphanDesc",
        "running",
        "settings.backupError",
        "settings.deleteError",
        "settings.restoreError",
        "settings.saving",
        "system.colMessage",
        "system.colSource",
        "system.colUser",
        "system.typeAudit",
        "system.typeHealth",
        "timeline.label.audio_change",
        "timeline.label.default",
        "timeline.label.pause",
        "timeline.label.seek",
        "timeline.label.stop",
        "timeline.label.subtitle_change",
        "timeline.legend.audio",
        "timeline.legend.pause",
        "timeline.legend.subtitles",
        "timeline.noEvents",
        "timeline.stop",
        "timeline.title",
        "timeline.toggle.exact"
      ],
      "extraCount": 319,
      "extraSample": [
        "about.featuresList",
        "about.techCron",
        "about.techNextAuth",
        "about.techNextjs",
        "about.techPrisma",
        "about.techReact",
        "about.techRecharts",
        "about.version",
        "charts.maxActiveStreams",
        "charts.play",
        "charts.plays",
        "charts.playsCount",
        "charts.playsInYear",
        "charts.playsTotal",
        "charts.viewsTotal",
        "cleanup.abandoned",
        "cleanup.deleteDialogConfirmInputLabel",
        "cleanup.deleteDialogDescription",
        "cleanup.deleteDialogTitle",
        "cleanup.deleteToastPartialError",
        "cleanup.deleteToastSuccess",
        "cleanup.staleMoviesRecommendationDesc",
        "common.apply",
        "common.filmsuhd",
        "common.hour",
        "common.hours",
        "common.livetv",
        "common.local",
        "common.more",
        "common.musiques",
        "common.on",
        "common.photos",
        "common.refresh",
        "common.seriesuhd",
        "common.source",
        "common.unknownDevice",
        "common.unknownSeries",
        "common.viewers",
        "dashboard.aiRecommendations",
        "dashboard.anomalyBreakdownTitle",
        "dashboard.anomalyChartsDesc",
        "dashboard.anomalyChartsTitle",
        "dashboard.anomalyCumulativeImpact",
        "dashboard.anomalySyncSuccess",
        "dashboard.autoAvailability",
        "dashboard.autoAvailabilityDesc",
        "dashboard.backup",
        "dashboard.backupTaskDesc",
        "dashboard.basedOnProfile",
        "dashboard.cachedData",
        "dashboard.completionDisabled",
        "dashboard.cumulAllTime",
        "dashboard.cumulVsPrev",
        "dashboard.dbWithoutRedisDesc",
        "dashboard.excludedLibrariesDesc",
        "dashboard.excludedLibrariesTitle",
        "dashboard.file",
        "dashboard.filterCategories",
        "dashboard.hoursAgo",
        "dashboard.lastError",
        "dashboard.lastSuccess",
        "dashboard.libraryRules",
        "dashboard.libraryRulesDesc",
        "dashboard.liveNow",
        "dashboard.logHealthDesc",
        "dashboard.manage",
        "dashboard.mediaSettings",
        "dashboard.mediaSettingsDesc",
        "dashboard.metadataAllGood",
        "dashboard.metadataAudit",
        "dashboard.metadataAuditDesc",
        "dashboard.minutesAgo",
        "dashboard.missingActors",
        "dashboard.missingGenres",
        "dashboard.missingResolution",
        "dashboard.mode",
        "dashboard.monitorStatusOk",
        "dashboard.multiServerComparator.desc",
        "dashboard.multiServerComparator.disabled",
        "dashboard.multiServerComparator.title",
        "dashboard.noExcludedLibraries",
        "dashboard.noOrphanPlaybacks",
        "dashboard.none",
        "dashboard.onTotalRegistered",
        "dashboard.openedOn",
        "dashboard.orphanItems",
        "dashboard.orphanPlaybacksDesc",
        "dashboard.orphanPlaybacksTitle",
        "dashboard.overviewDesc",
        "dashboard.playbackHistoryNote",
        "dashboard.processingStatusDesc",
        "dashboard.processingStatusTitle",
        "dashboard.recentClosuresDesc",
        "dashboard.recentClosuresTitle",
        "dashboard.redisOrphan",
        "dashboard.redisOrphanDesc",
        "dashboard.restore",
        "dashboard.rulesDesc",
        "dashboard.rulesTitle",
        "dashboard.scheduleSettingsDesc",
        "dashboard.schedulerBackups",
        "dashboard.sync",
        "dashboard.uncheckToHide",
        "dashboard.vsPrevPeriod",
        "dashboard.vsUsersOnPeriod",
        "dashboard.worldMap",
        "dashboard.worldMapDesc",
        "deepInsights.noDataSmall",
        "granular.durationByLibrary",
        "granular.durationByLibraryDesc",
        "granular.playsByLibrary",
        "granular.playsByLibraryDesc",
        "hardware.ram",
        "killStream.confirm",
        "liveStreams.description",
        "logs.activeFilter",
        "logs.audioFilter",
        "logs.booksFilter",
        "logs.clientFilter",
        "logs.dateFrom",
        "logs.dateTo",
        "logs.episodeType",
        "logs.movieType",
        "logs.moviesFilter",
        "logs.musicFilter",
        "logs.musicType",
        "logs.removeFilter",
        "logs.searchFilters",
        "logs.searchFiltersDesc",
        "logs.seasonType",
        "logs.seriesFilter",
        "logs.smartIpBurstItem",
        "logs.smartIpBurstTag",
        "logs.smartNewCountryDesc",
        "logs.subtitleFilter",
        "logs.timeline.label.audio_change",
        "logs.timeline.label.default",
        "logs.timeline.label.pause",
        "logs.timeline.label.seek",
        "logs.timeline.label.stop",
        "logs.timeline.label.subtitle_change",
        "logs.timeline.legend.audio",
        "logs.timeline.legend.pause",
        "logs.timeline.legend.subtitles",
        "logs.timeline.noEvents",
        "logs.timeline.stop",
        "logs.timeline.title",
        "logs.timeline.toggle.30s",
        "logs.timeline.toggle.5s",
        "logs.timeline.toggle.exact",
        "logs.typeFilter",
        "media.albumBadge",
        "media.audioFormats",
        "media.audioFormatsDesc",
        "media.audioOtherLabel",
        "media.availableContent",
        "media.flacLabel",
        "media.mp3Label",
        "media.noMedia",
        "media.seriesBadge",
        "media.sortBy",
        "media.sortPlayMode",
        "media.sortPopularity",
        "media.sortWatchTime",
        "media.timeDays",
        "media.title",
        "media.topDirectors",
        "mediaProfile.dropoff",
        "mediaProfile.dropoff0",
        "mediaProfile.dropoff1",
        "mediaProfile.dropoff2",
        "mediaProfile.dropoff3",
        "mediaProfile.dropoff4",
        "mediaProfile.dropoff5",
        "mediaProfile.dropoff6",
        "mediaProfile.dropoff7",
        "mediaProfile.dropoff8",
        "mediaProfile.dropoff9",
        "mediaProfile.episodes",
        "mediaProfile.markerCreditsStart",
        "mediaProfile.markerCustom",
        "mediaProfile.markerIntroEnd",
        "mediaProfile.markerIntroStart",
        "mediaProfile.seasons",
        "mediaProfile.sessionsTotal",
        "mediaProfile.stoppedAt",
        "mediaProfile.timeline.label.audio_change",
        "mediaProfile.timeline.label.pause",
        "mediaProfile.timeline.label.stop",
        "mediaProfile.timeline.label.subtitle_change",
        "mediaProfile.timeline_audio_change",
        "mediaProfile.timeline_pause",
        "mediaProfile.timeline_stop",
        "mediaProfile.timeline_subtitle_change",
        "mediaProfile.tracks",
        "mediaProfile.viewAlbum",
        "mediaProfile.viewSeries",
        "mediaProfile.viewers",
        "nav.cleanup",
        "nav.dashboard"
      ]
    },
    "nl.json": {
      "localeKeyCount": 1032,
      "missingCount": 55,
      "missingSample": [
        "anomalyChartsDesc",
        "anomalyChartsTitle",
        "charts.viewLogs",
        "common.directStream",
        "dbWithoutRedis",
        "dbWithoutRedisDesc",
        "excludedLibrariesDesc",
        "excludedLibrariesTitle",
        "granular.unknown",
        "lastPoll",
        "liveStreams.unknown",
        "logHealth",
        "logHealthDesc",
        "logs.tabApplication",
        "logs.tabSystem",
        "monitor",
        "monitorStatusError",
        "monitorStatusOk",
        "multiServerComparator.desc",
        "multiServerComparator.disabled",
        "multiServerComparator.title",
        "never",
        "noExcludedLibraries",
        "noOrphanPlaybacks",
        "openPlaybackOrphans",
        "orphanPlaybacksDesc",
        "orphanPlaybacksTitle",
        "playbackHistoryNote",
        "recentClosuresDesc",
        "recentClosuresTitle",
        "redisOrphan",
        "redisOrphanDesc",
        "running",
        "settings.backupError",
        "settings.deleteError",
        "settings.restoreError",
        "settings.saving",
        "system.colMessage",
        "system.colSource",
        "system.colUser",
        "system.typeAudit",
        "system.typeHealth",
        "timeline.label.audio_change",
        "timeline.label.default",
        "timeline.label.pause",
        "timeline.label.seek",
        "timeline.label.stop",
        "timeline.label.subtitle_change",
        "timeline.legend.audio",
        "timeline.legend.pause",
        "timeline.legend.subtitles",
        "timeline.noEvents",
        "timeline.stop",
        "timeline.title",
        "timeline.toggle.exact"
      ],
      "extraCount": 319,
      "extraSample": [
        "about.featuresList",
        "about.techCron",
        "about.techNextAuth",
        "about.techNextjs",
        "about.techPrisma",
        "about.techReact",
        "about.techRecharts",
        "about.version",
        "charts.maxActiveStreams",
        "charts.play",
        "charts.plays",
        "charts.playsCount",
        "charts.playsInYear",
        "charts.playsTotal",
        "charts.viewsTotal",
        "cleanup.abandoned",
        "cleanup.deleteDialogConfirmInputLabel",
        "cleanup.deleteDialogDescription",
        "cleanup.deleteDialogTitle",
        "cleanup.deleteToastPartialError",
        "cleanup.deleteToastSuccess",
        "cleanup.staleMoviesRecommendationDesc",
        "common.apply",
        "common.filmsuhd",
        "common.hour",
        "common.hours",
        "common.livetv",
        "common.local",
        "common.more",
        "common.musiques",
        "common.on",
        "common.photos",
        "common.refresh",
        "common.seriesuhd",
        "common.source",
        "common.unknownDevice",
        "common.unknownSeries",
        "common.viewers",
        "dashboard.aiRecommendations",
        "dashboard.anomalyBreakdownTitle",
        "dashboard.anomalyChartsDesc",
        "dashboard.anomalyChartsTitle",
        "dashboard.anomalyCumulativeImpact",
        "dashboard.anomalySyncSuccess",
        "dashboard.autoAvailability",
        "dashboard.autoAvailabilityDesc",
        "dashboard.backup",
        "dashboard.backupTaskDesc",
        "dashboard.basedOnProfile",
        "dashboard.cachedData",
        "dashboard.completionDisabled",
        "dashboard.cumulAllTime",
        "dashboard.cumulVsPrev",
        "dashboard.dbWithoutRedisDesc",
        "dashboard.excludedLibrariesDesc",
        "dashboard.excludedLibrariesTitle",
        "dashboard.file",
        "dashboard.filterCategories",
        "dashboard.hoursAgo",
        "dashboard.lastError",
        "dashboard.lastSuccess",
        "dashboard.libraryRules",
        "dashboard.libraryRulesDesc",
        "dashboard.liveNow",
        "dashboard.logHealthDesc",
        "dashboard.manage",
        "dashboard.mediaSettings",
        "dashboard.mediaSettingsDesc",
        "dashboard.metadataAllGood",
        "dashboard.metadataAudit",
        "dashboard.metadataAuditDesc",
        "dashboard.minutesAgo",
        "dashboard.missingActors",
        "dashboard.missingGenres",
        "dashboard.missingResolution",
        "dashboard.mode",
        "dashboard.monitorStatusOk",
        "dashboard.multiServerComparator.desc",
        "dashboard.multiServerComparator.disabled",
        "dashboard.multiServerComparator.title",
        "dashboard.noExcludedLibraries",
        "dashboard.noOrphanPlaybacks",
        "dashboard.none",
        "dashboard.onTotalRegistered",
        "dashboard.openedOn",
        "dashboard.orphanItems",
        "dashboard.orphanPlaybacksDesc",
        "dashboard.orphanPlaybacksTitle",
        "dashboard.overviewDesc",
        "dashboard.playbackHistoryNote",
        "dashboard.processingStatusDesc",
        "dashboard.processingStatusTitle",
        "dashboard.recentClosuresDesc",
        "dashboard.recentClosuresTitle",
        "dashboard.redisOrphan",
        "dashboard.redisOrphanDesc",
        "dashboard.restore",
        "dashboard.rulesDesc",
        "dashboard.rulesTitle",
        "dashboard.scheduleSettingsDesc",
        "dashboard.schedulerBackups",
        "dashboard.sync",
        "dashboard.uncheckToHide",
        "dashboard.vsPrevPeriod",
        "dashboard.vsUsersOnPeriod",
        "dashboard.worldMap",
        "dashboard.worldMapDesc",
        "deepInsights.noDataSmall",
        "granular.durationByLibrary",
        "granular.durationByLibraryDesc",
        "granular.playsByLibrary",
        "granular.playsByLibraryDesc",
        "hardware.ram",
        "killStream.confirm",
        "liveStreams.description",
        "logs.activeFilter",
        "logs.audioFilter",
        "logs.booksFilter",
        "logs.clientFilter",
        "logs.dateFrom",
        "logs.dateTo",
        "logs.episodeType",
        "logs.movieType",
        "logs.moviesFilter",
        "logs.musicFilter",
        "logs.musicType",
        "logs.removeFilter",
        "logs.searchFilters",
        "logs.searchFiltersDesc",
        "logs.seasonType",
        "logs.seriesFilter",
        "logs.smartIpBurstItem",
        "logs.smartIpBurstTag",
        "logs.smartNewCountryDesc",
        "logs.subtitleFilter",
        "logs.timeline.label.audio_change",
        "logs.timeline.label.default",
        "logs.timeline.label.pause",
        "logs.timeline.label.seek",
        "logs.timeline.label.stop",
        "logs.timeline.label.subtitle_change",
        "logs.timeline.legend.audio",
        "logs.timeline.legend.pause",
        "logs.timeline.legend.subtitles",
        "logs.timeline.noEvents",
        "logs.timeline.stop",
        "logs.timeline.title",
        "logs.timeline.toggle.30s",
        "logs.timeline.toggle.5s",
        "logs.timeline.toggle.exact",
        "logs.typeFilter",
        "media.albumBadge",
        "media.audioFormats",
        "media.audioFormatsDesc",
        "media.audioOtherLabel",
        "media.availableContent",
        "media.flacLabel",
        "media.mp3Label",
        "media.noMedia",
        "media.seriesBadge",
        "media.sortBy",
        "media.sortPlayMode",
        "media.sortPopularity",
        "media.sortWatchTime",
        "media.timeDays",
        "media.title",
        "media.topDirectors",
        "mediaProfile.dropoff",
        "mediaProfile.dropoff0",
        "mediaProfile.dropoff1",
        "mediaProfile.dropoff2",
        "mediaProfile.dropoff3",
        "mediaProfile.dropoff4",
        "mediaProfile.dropoff5",
        "mediaProfile.dropoff6",
        "mediaProfile.dropoff7",
        "mediaProfile.dropoff8",
        "mediaProfile.dropoff9",
        "mediaProfile.episodes",
        "mediaProfile.markerCreditsStart",
        "mediaProfile.markerCustom",
        "mediaProfile.markerIntroEnd",
        "mediaProfile.markerIntroStart",
        "mediaProfile.seasons",
        "mediaProfile.sessionsTotal",
        "mediaProfile.stoppedAt",
        "mediaProfile.timeline.label.audio_change",
        "mediaProfile.timeline.label.pause",
        "mediaProfile.timeline.label.stop",
        "mediaProfile.timeline.label.subtitle_change",
        "mediaProfile.timeline_audio_change",
        "mediaProfile.timeline_pause",
        "mediaProfile.timeline_stop",
        "mediaProfile.timeline_subtitle_change",
        "mediaProfile.tracks",
        "mediaProfile.viewAlbum",
        "mediaProfile.viewSeries",
        "mediaProfile.viewers",
        "nav.cleanup",
        "nav.dashboard"
      ]
    },
    "pl.json": {
      "localeKeyCount": 1032,
      "missingCount": 55,
      "missingSample": [
        "anomalyChartsDesc",
        "anomalyChartsTitle",
        "charts.viewLogs",
        "common.directStream",
        "dbWithoutRedis",
        "dbWithoutRedisDesc",
        "excludedLibrariesDesc",
        "excludedLibrariesTitle",
        "granular.unknown",
        "lastPoll",
        "liveStreams.unknown",
        "logHealth",
        "logHealthDesc",
        "logs.tabApplication",
        "logs.tabSystem",
        "monitor",
        "monitorStatusError",
        "monitorStatusOk",
        "multiServerComparator.desc",
        "multiServerComparator.disabled",
        "multiServerComparator.title",
        "never",
        "noExcludedLibraries",
        "noOrphanPlaybacks",
        "openPlaybackOrphans",
        "orphanPlaybacksDesc",
        "orphanPlaybacksTitle",
        "playbackHistoryNote",
        "recentClosuresDesc",
        "recentClosuresTitle",
        "redisOrphan",
        "redisOrphanDesc",
        "running",
        "settings.backupError",
        "settings.deleteError",
        "settings.restoreError",
        "settings.saving",
        "system.colMessage",
        "system.colSource",
        "system.colUser",
        "system.typeAudit",
        "system.typeHealth",
        "timeline.label.audio_change",
        "timeline.label.default",
        "timeline.label.pause",
        "timeline.label.seek",
        "timeline.label.stop",
        "timeline.label.subtitle_change",
        "timeline.legend.audio",
        "timeline.legend.pause",
        "timeline.legend.subtitles",
        "timeline.noEvents",
        "timeline.stop",
        "timeline.title",
        "timeline.toggle.exact"
      ],
      "extraCount": 319,
      "extraSample": [
        "about.featuresList",
        "about.techCron",
        "about.techNextAuth",
        "about.techNextjs",
        "about.techPrisma",
        "about.techReact",
        "about.techRecharts",
        "about.version",
        "charts.maxActiveStreams",
        "charts.play",
        "charts.plays",
        "charts.playsCount",
        "charts.playsInYear",
        "charts.playsTotal",
        "charts.viewsTotal",
        "cleanup.abandoned",
        "cleanup.deleteDialogConfirmInputLabel",
        "cleanup.deleteDialogDescription",
        "cleanup.deleteDialogTitle",
        "cleanup.deleteToastPartialError",
        "cleanup.deleteToastSuccess",
        "cleanup.staleMoviesRecommendationDesc",
        "common.apply",
        "common.filmsuhd",
        "common.hour",
        "common.hours",
        "common.livetv",
        "common.local",
        "common.more",
        "common.musiques",
        "common.on",
        "common.photos",
        "common.refresh",
        "common.seriesuhd",
        "common.source",
        "common.unknownDevice",
        "common.unknownSeries",
        "common.viewers",
        "dashboard.aiRecommendations",
        "dashboard.anomalyBreakdownTitle",
        "dashboard.anomalyChartsDesc",
        "dashboard.anomalyChartsTitle",
        "dashboard.anomalyCumulativeImpact",
        "dashboard.anomalySyncSuccess",
        "dashboard.autoAvailability",
        "dashboard.autoAvailabilityDesc",
        "dashboard.backup",
        "dashboard.backupTaskDesc",
        "dashboard.basedOnProfile",
        "dashboard.cachedData",
        "dashboard.completionDisabled",
        "dashboard.cumulAllTime",
        "dashboard.cumulVsPrev",
        "dashboard.dbWithoutRedisDesc",
        "dashboard.excludedLibrariesDesc",
        "dashboard.excludedLibrariesTitle",
        "dashboard.file",
        "dashboard.filterCategories",
        "dashboard.hoursAgo",
        "dashboard.lastError",
        "dashboard.lastSuccess",
        "dashboard.libraryRules",
        "dashboard.libraryRulesDesc",
        "dashboard.liveNow",
        "dashboard.logHealthDesc",
        "dashboard.manage",
        "dashboard.mediaSettings",
        "dashboard.mediaSettingsDesc",
        "dashboard.metadataAllGood",
        "dashboard.metadataAudit",
        "dashboard.metadataAuditDesc",
        "dashboard.minutesAgo",
        "dashboard.missingActors",
        "dashboard.missingGenres",
        "dashboard.missingResolution",
        "dashboard.mode",
        "dashboard.monitorStatusOk",
        "dashboard.multiServerComparator.desc",
        "dashboard.multiServerComparator.disabled",
        "dashboard.multiServerComparator.title",
        "dashboard.noExcludedLibraries",
        "dashboard.noOrphanPlaybacks",
        "dashboard.none",
        "dashboard.onTotalRegistered",
        "dashboard.openedOn",
        "dashboard.orphanItems",
        "dashboard.orphanPlaybacksDesc",
        "dashboard.orphanPlaybacksTitle",
        "dashboard.overviewDesc",
        "dashboard.playbackHistoryNote",
        "dashboard.processingStatusDesc",
        "dashboard.processingStatusTitle",
        "dashboard.recentClosuresDesc",
        "dashboard.recentClosuresTitle",
        "dashboard.redisOrphan",
        "dashboard.redisOrphanDesc",
        "dashboard.restore",
        "dashboard.rulesDesc",
        "dashboard.rulesTitle",
        "dashboard.scheduleSettingsDesc",
        "dashboard.schedulerBackups",
        "dashboard.sync",
        "dashboard.uncheckToHide",
        "dashboard.vsPrevPeriod",
        "dashboard.vsUsersOnPeriod",
        "dashboard.worldMap",
        "dashboard.worldMapDesc",
        "deepInsights.noDataSmall",
        "granular.durationByLibrary",
        "granular.durationByLibraryDesc",
        "granular.playsByLibrary",
        "granular.playsByLibraryDesc",
        "hardware.ram",
        "killStream.confirm",
        "liveStreams.description",
        "logs.activeFilter",
        "logs.audioFilter",
        "logs.booksFilter",
        "logs.clientFilter",
        "logs.dateFrom",
        "logs.dateTo",
        "logs.episodeType",
        "logs.movieType",
        "logs.moviesFilter",
        "logs.musicFilter",
        "logs.musicType",
        "logs.removeFilter",
        "logs.searchFilters",
        "logs.searchFiltersDesc",
        "logs.seasonType",
        "logs.seriesFilter",
        "logs.smartIpBurstItem",
        "logs.smartIpBurstTag",
        "logs.smartNewCountryDesc",
        "logs.subtitleFilter",
        "logs.timeline.label.audio_change",
        "logs.timeline.label.default",
        "logs.timeline.label.pause",
        "logs.timeline.label.seek",
        "logs.timeline.label.stop",
        "logs.timeline.label.subtitle_change",
        "logs.timeline.legend.audio",
        "logs.timeline.legend.pause",
        "logs.timeline.legend.subtitles",
        "logs.timeline.noEvents",
        "logs.timeline.stop",
        "logs.timeline.title",
        "logs.timeline.toggle.30s",
        "logs.timeline.toggle.5s",
        "logs.timeline.toggle.exact",
        "logs.typeFilter",
        "media.albumBadge",
        "media.audioFormats",
        "media.audioFormatsDesc",
        "media.audioOtherLabel",
        "media.availableContent",
        "media.flacLabel",
        "media.mp3Label",
        "media.noMedia",
        "media.seriesBadge",
        "media.sortBy",
        "media.sortPlayMode",
        "media.sortPopularity",
        "media.sortWatchTime",
        "media.timeDays",
        "media.title",
        "media.topDirectors",
        "mediaProfile.dropoff",
        "mediaProfile.dropoff0",
        "mediaProfile.dropoff1",
        "mediaProfile.dropoff2",
        "mediaProfile.dropoff3",
        "mediaProfile.dropoff4",
        "mediaProfile.dropoff5",
        "mediaProfile.dropoff6",
        "mediaProfile.dropoff7",
        "mediaProfile.dropoff8",
        "mediaProfile.dropoff9",
        "mediaProfile.episodes",
        "mediaProfile.markerCreditsStart",
        "mediaProfile.markerCustom",
        "mediaProfile.markerIntroEnd",
        "mediaProfile.markerIntroStart",
        "mediaProfile.seasons",
        "mediaProfile.sessionsTotal",
        "mediaProfile.stoppedAt",
        "mediaProfile.timeline.label.audio_change",
        "mediaProfile.timeline.label.pause",
        "mediaProfile.timeline.label.stop",
        "mediaProfile.timeline.label.subtitle_change",
        "mediaProfile.timeline_audio_change",
        "mediaProfile.timeline_pause",
        "mediaProfile.timeline_stop",
        "mediaProfile.timeline_subtitle_change",
        "mediaProfile.tracks",
        "mediaProfile.viewAlbum",
        "mediaProfile.viewSeries",
        "mediaProfile.viewers",
        "nav.cleanup",
        "nav.dashboard"
      ]
    },
    "pt-BR.json": {
      "localeKeyCount": 1032,
      "missingCount": 55,
      "missingSample": [
        "anomalyChartsDesc",
        "anomalyChartsTitle",
        "charts.viewLogs",
        "common.directStream",
        "dbWithoutRedis",
        "dbWithoutRedisDesc",
        "excludedLibrariesDesc",
        "excludedLibrariesTitle",
        "granular.unknown",
        "lastPoll",
        "liveStreams.unknown",
        "logHealth",
        "logHealthDesc",
        "logs.tabApplication",
        "logs.tabSystem",
        "monitor",
        "monitorStatusError",
        "monitorStatusOk",
        "multiServerComparator.desc",
        "multiServerComparator.disabled",
        "multiServerComparator.title",
        "never",
        "noExcludedLibraries",
        "noOrphanPlaybacks",
        "openPlaybackOrphans",
        "orphanPlaybacksDesc",
        "orphanPlaybacksTitle",
        "playbackHistoryNote",
        "recentClosuresDesc",
        "recentClosuresTitle",
        "redisOrphan",
        "redisOrphanDesc",
        "running",
        "settings.backupError",
        "settings.deleteError",
        "settings.restoreError",
        "settings.saving",
        "system.colMessage",
        "system.colSource",
        "system.colUser",
        "system.typeAudit",
        "system.typeHealth",
        "timeline.label.audio_change",
        "timeline.label.default",
        "timeline.label.pause",
        "timeline.label.seek",
        "timeline.label.stop",
        "timeline.label.subtitle_change",
        "timeline.legend.audio",
        "timeline.legend.pause",
        "timeline.legend.subtitles",
        "timeline.noEvents",
        "timeline.stop",
        "timeline.title",
        "timeline.toggle.exact"
      ],
      "extraCount": 319,
      "extraSample": [
        "about.featuresList",
        "about.techCron",
        "about.techNextAuth",
        "about.techNextjs",
        "about.techPrisma",
        "about.techReact",
        "about.techRecharts",
        "about.version",
        "charts.maxActiveStreams",
        "charts.play",
        "charts.plays",
        "charts.playsCount",
        "charts.playsInYear",
        "charts.playsTotal",
        "charts.viewsTotal",
        "cleanup.abandoned",
        "cleanup.deleteDialogConfirmInputLabel",
        "cleanup.deleteDialogDescription",
        "cleanup.deleteDialogTitle",
        "cleanup.deleteToastPartialError",
        "cleanup.deleteToastSuccess",
        "cleanup.staleMoviesRecommendationDesc",
        "common.apply",
        "common.filmsuhd",
        "common.hour",
        "common.hours",
        "common.livetv",
        "common.local",
        "common.more",
        "common.musiques",
        "common.on",
        "common.photos",
        "common.refresh",
        "common.seriesuhd",
        "common.source",
        "common.unknownDevice",
        "common.unknownSeries",
        "common.viewers",
        "dashboard.aiRecommendations",
        "dashboard.anomalyBreakdownTitle",
        "dashboard.anomalyChartsDesc",
        "dashboard.anomalyChartsTitle",
        "dashboard.anomalyCumulativeImpact",
        "dashboard.anomalySyncSuccess",
        "dashboard.autoAvailability",
        "dashboard.autoAvailabilityDesc",
        "dashboard.backup",
        "dashboard.backupTaskDesc",
        "dashboard.basedOnProfile",
        "dashboard.cachedData",
        "dashboard.completionDisabled",
        "dashboard.cumulAllTime",
        "dashboard.cumulVsPrev",
        "dashboard.dbWithoutRedisDesc",
        "dashboard.excludedLibrariesDesc",
        "dashboard.excludedLibrariesTitle",
        "dashboard.file",
        "dashboard.filterCategories",
        "dashboard.hoursAgo",
        "dashboard.lastError",
        "dashboard.lastSuccess",
        "dashboard.libraryRules",
        "dashboard.libraryRulesDesc",
        "dashboard.liveNow",
        "dashboard.logHealthDesc",
        "dashboard.manage",
        "dashboard.mediaSettings",
        "dashboard.mediaSettingsDesc",
        "dashboard.metadataAllGood",
        "dashboard.metadataAudit",
        "dashboard.metadataAuditDesc",
        "dashboard.minutesAgo",
        "dashboard.missingActors",
        "dashboard.missingGenres",
        "dashboard.missingResolution",
        "dashboard.mode",
        "dashboard.monitorStatusOk",
        "dashboard.multiServerComparator.desc",
        "dashboard.multiServerComparator.disabled",
        "dashboard.multiServerComparator.title",
        "dashboard.noExcludedLibraries",
        "dashboard.noOrphanPlaybacks",
        "dashboard.none",
        "dashboard.onTotalRegistered",
        "dashboard.openedOn",
        "dashboard.orphanItems",
        "dashboard.orphanPlaybacksDesc",
        "dashboard.orphanPlaybacksTitle",
        "dashboard.overviewDesc",
        "dashboard.playbackHistoryNote",
        "dashboard.processingStatusDesc",
        "dashboard.processingStatusTitle",
        "dashboard.recentClosuresDesc",
        "dashboard.recentClosuresTitle",
        "dashboard.redisOrphan",
        "dashboard.redisOrphanDesc",
        "dashboard.restore",
        "dashboard.rulesDesc",
        "dashboard.rulesTitle",
        "dashboard.scheduleSettingsDesc",
        "dashboard.schedulerBackups",
        "dashboard.sync",
        "dashboard.uncheckToHide",
        "dashboard.vsPrevPeriod",
        "dashboard.vsUsersOnPeriod",
        "dashboard.worldMap",
        "dashboard.worldMapDesc",
        "deepInsights.noDataSmall",
        "granular.durationByLibrary",
        "granular.durationByLibraryDesc",
        "granular.playsByLibrary",
        "granular.playsByLibraryDesc",
        "hardware.ram",
        "killStream.confirm",
        "liveStreams.description",
        "logs.activeFilter",
        "logs.audioFilter",
        "logs.booksFilter",
        "logs.clientFilter",
        "logs.dateFrom",
        "logs.dateTo",
        "logs.episodeType",
        "logs.movieType",
        "logs.moviesFilter",
        "logs.musicFilter",
        "logs.musicType",
        "logs.removeFilter",
        "logs.searchFilters",
        "logs.searchFiltersDesc",
        "logs.seasonType",
        "logs.seriesFilter",
        "logs.smartIpBurstItem",
        "logs.smartIpBurstTag",
        "logs.smartNewCountryDesc",
        "logs.subtitleFilter",
        "logs.timeline.label.audio_change",
        "logs.timeline.label.default",
        "logs.timeline.label.pause",
        "logs.timeline.label.seek",
        "logs.timeline.label.stop",
        "logs.timeline.label.subtitle_change",
        "logs.timeline.legend.audio",
        "logs.timeline.legend.pause",
        "logs.timeline.legend.subtitles",
        "logs.timeline.noEvents",
        "logs.timeline.stop",
        "logs.timeline.title",
        "logs.timeline.toggle.30s",
        "logs.timeline.toggle.5s",
        "logs.timeline.toggle.exact",
        "logs.typeFilter",
        "media.albumBadge",
        "media.audioFormats",
        "media.audioFormatsDesc",
        "media.audioOtherLabel",
        "media.availableContent",
        "media.flacLabel",
        "media.mp3Label",
        "media.noMedia",
        "media.seriesBadge",
        "media.sortBy",
        "media.sortPlayMode",
        "media.sortPopularity",
        "media.sortWatchTime",
        "media.timeDays",
        "media.title",
        "media.topDirectors",
        "mediaProfile.dropoff",
        "mediaProfile.dropoff0",
        "mediaProfile.dropoff1",
        "mediaProfile.dropoff2",
        "mediaProfile.dropoff3",
        "mediaProfile.dropoff4",
        "mediaProfile.dropoff5",
        "mediaProfile.dropoff6",
        "mediaProfile.dropoff7",
        "mediaProfile.dropoff8",
        "mediaProfile.dropoff9",
        "mediaProfile.episodes",
        "mediaProfile.markerCreditsStart",
        "mediaProfile.markerCustom",
        "mediaProfile.markerIntroEnd",
        "mediaProfile.markerIntroStart",
        "mediaProfile.seasons",
        "mediaProfile.sessionsTotal",
        "mediaProfile.stoppedAt",
        "mediaProfile.timeline.label.audio_change",
        "mediaProfile.timeline.label.pause",
        "mediaProfile.timeline.label.stop",
        "mediaProfile.timeline.label.subtitle_change",
        "mediaProfile.timeline_audio_change",
        "mediaProfile.timeline_pause",
        "mediaProfile.timeline_stop",
        "mediaProfile.timeline_subtitle_change",
        "mediaProfile.tracks",
        "mediaProfile.viewAlbum",
        "mediaProfile.viewSeries",
        "mediaProfile.viewers",
        "nav.cleanup",
        "nav.dashboard"
      ]
    },
    "ru.json": {
      "localeKeyCount": 1032,
      "missingCount": 55,
      "missingSample": [
        "anomalyChartsDesc",
        "anomalyChartsTitle",
        "charts.viewLogs",
        "common.directStream",
        "dbWithoutRedis",
        "dbWithoutRedisDesc",
        "excludedLibrariesDesc",
        "excludedLibrariesTitle",
        "granular.unknown",
        "lastPoll",
        "liveStreams.unknown",
        "logHealth",
        "logHealthDesc",
        "logs.tabApplication",
        "logs.tabSystem",
        "monitor",
        "monitorStatusError",
        "monitorStatusOk",
        "multiServerComparator.desc",
        "multiServerComparator.disabled",
        "multiServerComparator.title",
        "never",
        "noExcludedLibraries",
        "noOrphanPlaybacks",
        "openPlaybackOrphans",
        "orphanPlaybacksDesc",
        "orphanPlaybacksTitle",
        "playbackHistoryNote",
        "recentClosuresDesc",
        "recentClosuresTitle",
        "redisOrphan",
        "redisOrphanDesc",
        "running",
        "settings.backupError",
        "settings.deleteError",
        "settings.restoreError",
        "settings.saving",
        "system.colMessage",
        "system.colSource",
        "system.colUser",
        "system.typeAudit",
        "system.typeHealth",
        "timeline.label.audio_change",
        "timeline.label.default",
        "timeline.label.pause",
        "timeline.label.seek",
        "timeline.label.stop",
        "timeline.label.subtitle_change",
        "timeline.legend.audio",
        "timeline.legend.pause",
        "timeline.legend.subtitles",
        "timeline.noEvents",
        "timeline.stop",
        "timeline.title",
        "timeline.toggle.exact"
      ],
      "extraCount": 319,
      "extraSample": [
        "about.featuresList",
        "about.techCron",
        "about.techNextAuth",
        "about.techNextjs",
        "about.techPrisma",
        "about.techReact",
        "about.techRecharts",
        "about.version",
        "charts.maxActiveStreams",
        "charts.play",
        "charts.plays",
        "charts.playsCount",
        "charts.playsInYear",
        "charts.playsTotal",
        "charts.viewsTotal",
        "cleanup.abandoned",
        "cleanup.deleteDialogConfirmInputLabel",
        "cleanup.deleteDialogDescription",
        "cleanup.deleteDialogTitle",
        "cleanup.deleteToastPartialError",
        "cleanup.deleteToastSuccess",
        "cleanup.staleMoviesRecommendationDesc",
        "common.apply",
        "common.filmsuhd",
        "common.hour",
        "common.hours",
        "common.livetv",
        "common.local",
        "common.more",
        "common.musiques",
        "common.on",
        "common.photos",
        "common.refresh",
        "common.seriesuhd",
        "common.source",
        "common.unknownDevice",
        "common.unknownSeries",
        "common.viewers",
        "dashboard.aiRecommendations",
        "dashboard.anomalyBreakdownTitle",
        "dashboard.anomalyChartsDesc",
        "dashboard.anomalyChartsTitle",
        "dashboard.anomalyCumulativeImpact",
        "dashboard.anomalySyncSuccess",
        "dashboard.autoAvailability",
        "dashboard.autoAvailabilityDesc",
        "dashboard.backup",
        "dashboard.backupTaskDesc",
        "dashboard.basedOnProfile",
        "dashboard.cachedData",
        "dashboard.completionDisabled",
        "dashboard.cumulAllTime",
        "dashboard.cumulVsPrev",
        "dashboard.dbWithoutRedisDesc",
        "dashboard.excludedLibrariesDesc",
        "dashboard.excludedLibrariesTitle",
        "dashboard.file",
        "dashboard.filterCategories",
        "dashboard.hoursAgo",
        "dashboard.lastError",
        "dashboard.lastSuccess",
        "dashboard.libraryRules",
        "dashboard.libraryRulesDesc",
        "dashboard.liveNow",
        "dashboard.logHealthDesc",
        "dashboard.manage",
        "dashboard.mediaSettings",
        "dashboard.mediaSettingsDesc",
        "dashboard.metadataAllGood",
        "dashboard.metadataAudit",
        "dashboard.metadataAuditDesc",
        "dashboard.minutesAgo",
        "dashboard.missingActors",
        "dashboard.missingGenres",
        "dashboard.missingResolution",
        "dashboard.mode",
        "dashboard.monitorStatusOk",
        "dashboard.multiServerComparator.desc",
        "dashboard.multiServerComparator.disabled",
        "dashboard.multiServerComparator.title",
        "dashboard.noExcludedLibraries",
        "dashboard.noOrphanPlaybacks",
        "dashboard.none",
        "dashboard.onTotalRegistered",
        "dashboard.openedOn",
        "dashboard.orphanItems",
        "dashboard.orphanPlaybacksDesc",
        "dashboard.orphanPlaybacksTitle",
        "dashboard.overviewDesc",
        "dashboard.playbackHistoryNote",
        "dashboard.processingStatusDesc",
        "dashboard.processingStatusTitle",
        "dashboard.recentClosuresDesc",
        "dashboard.recentClosuresTitle",
        "dashboard.redisOrphan",
        "dashboard.redisOrphanDesc",
        "dashboard.restore",
        "dashboard.rulesDesc",
        "dashboard.rulesTitle",
        "dashboard.scheduleSettingsDesc",
        "dashboard.schedulerBackups",
        "dashboard.sync",
        "dashboard.uncheckToHide",
        "dashboard.vsPrevPeriod",
        "dashboard.vsUsersOnPeriod",
        "dashboard.worldMap",
        "dashboard.worldMapDesc",
        "deepInsights.noDataSmall",
        "granular.durationByLibrary",
        "granular.durationByLibraryDesc",
        "granular.playsByLibrary",
        "granular.playsByLibraryDesc",
        "hardware.ram",
        "killStream.confirm",
        "liveStreams.description",
        "logs.activeFilter",
        "logs.audioFilter",
        "logs.booksFilter",
        "logs.clientFilter",
        "logs.dateFrom",
        "logs.dateTo",
        "logs.episodeType",
        "logs.movieType",
        "logs.moviesFilter",
        "logs.musicFilter",
        "logs.musicType",
        "logs.removeFilter",
        "logs.searchFilters",
        "logs.searchFiltersDesc",
        "logs.seasonType",
        "logs.seriesFilter",
        "logs.smartIpBurstItem",
        "logs.smartIpBurstTag",
        "logs.smartNewCountryDesc",
        "logs.subtitleFilter",
        "logs.timeline.label.audio_change",
        "logs.timeline.label.default",
        "logs.timeline.label.pause",
        "logs.timeline.label.seek",
        "logs.timeline.label.stop",
        "logs.timeline.label.subtitle_change",
        "logs.timeline.legend.audio",
        "logs.timeline.legend.pause",
        "logs.timeline.legend.subtitles",
        "logs.timeline.noEvents",
        "logs.timeline.stop",
        "logs.timeline.title",
        "logs.timeline.toggle.30s",
        "logs.timeline.toggle.5s",
        "logs.timeline.toggle.exact",
        "logs.typeFilter",
        "media.albumBadge",
        "media.audioFormats",
        "media.audioFormatsDesc",
        "media.audioOtherLabel",
        "media.availableContent",
        "media.flacLabel",
        "media.mp3Label",
        "media.noMedia",
        "media.seriesBadge",
        "media.sortBy",
        "media.sortPlayMode",
        "media.sortPopularity",
        "media.sortWatchTime",
        "media.timeDays",
        "media.title",
        "media.topDirectors",
        "mediaProfile.dropoff",
        "mediaProfile.dropoff0",
        "mediaProfile.dropoff1",
        "mediaProfile.dropoff2",
        "mediaProfile.dropoff3",
        "mediaProfile.dropoff4",
        "mediaProfile.dropoff5",
        "mediaProfile.dropoff6",
        "mediaProfile.dropoff7",
        "mediaProfile.dropoff8",
        "mediaProfile.dropoff9",
        "mediaProfile.episodes",
        "mediaProfile.markerCreditsStart",
        "mediaProfile.markerCustom",
        "mediaProfile.markerIntroEnd",
        "mediaProfile.markerIntroStart",
        "mediaProfile.seasons",
        "mediaProfile.sessionsTotal",
        "mediaProfile.stoppedAt",
        "mediaProfile.timeline.label.audio_change",
        "mediaProfile.timeline.label.pause",
        "mediaProfile.timeline.label.stop",
        "mediaProfile.timeline.label.subtitle_change",
        "mediaProfile.timeline_audio_change",
        "mediaProfile.timeline_pause",
        "mediaProfile.timeline_stop",
        "mediaProfile.timeline_subtitle_change",
        "mediaProfile.tracks",
        "mediaProfile.viewAlbum",
        "mediaProfile.viewSeries",
        "mediaProfile.viewers",
        "nav.cleanup",
        "nav.dashboard"
      ]
    },
    "zh.json": {
      "localeKeyCount": 1032,
      "missingCount": 55,
      "missingSample": [
        "anomalyChartsDesc",
        "anomalyChartsTitle",
        "charts.viewLogs",
        "common.directStream",
        "dbWithoutRedis",
        "dbWithoutRedisDesc",
        "excludedLibrariesDesc",
        "excludedLibrariesTitle",
        "granular.unknown",
        "lastPoll",
        "liveStreams.unknown",
        "logHealth",
        "logHealthDesc",
        "logs.tabApplication",
        "logs.tabSystem",
        "monitor",
        "monitorStatusError",
        "monitorStatusOk",
        "multiServerComparator.desc",
        "multiServerComparator.disabled",
        "multiServerComparator.title",
        "never",
        "noExcludedLibraries",
        "noOrphanPlaybacks",
        "openPlaybackOrphans",
        "orphanPlaybacksDesc",
        "orphanPlaybacksTitle",
        "playbackHistoryNote",
        "recentClosuresDesc",
        "recentClosuresTitle",
        "redisOrphan",
        "redisOrphanDesc",
        "running",
        "settings.backupError",
        "settings.deleteError",
        "settings.restoreError",
        "settings.saving",
        "system.colMessage",
        "system.colSource",
        "system.colUser",
        "system.typeAudit",
        "system.typeHealth",
        "timeline.label.audio_change",
        "timeline.label.default",
        "timeline.label.pause",
        "timeline.label.seek",
        "timeline.label.stop",
        "timeline.label.subtitle_change",
        "timeline.legend.audio",
        "timeline.legend.pause",
        "timeline.legend.subtitles",
        "timeline.noEvents",
        "timeline.stop",
        "timeline.title",
        "timeline.toggle.exact"
      ],
      "extraCount": 319,
      "extraSample": [
        "about.featuresList",
        "about.techCron",
        "about.techNextAuth",
        "about.techNextjs",
        "about.techPrisma",
        "about.techReact",
        "about.techRecharts",
        "about.version",
        "charts.maxActiveStreams",
        "charts.play",
        "charts.plays",
        "charts.playsCount",
        "charts.playsInYear",
        "charts.playsTotal",
        "charts.viewsTotal",
        "cleanup.abandoned",
        "cleanup.deleteDialogConfirmInputLabel",
        "cleanup.deleteDialogDescription",
        "cleanup.deleteDialogTitle",
        "cleanup.deleteToastPartialError",
        "cleanup.deleteToastSuccess",
        "cleanup.staleMoviesRecommendationDesc",
        "common.apply",
        "common.filmsuhd",
        "common.hour",
        "common.hours",
        "common.livetv",
        "common.local",
        "common.more",
        "common.musiques",
        "common.on",
        "common.photos",
        "common.refresh",
        "common.seriesuhd",
        "common.source",
        "common.unknownDevice",
        "common.unknownSeries",
        "common.viewers",
        "dashboard.aiRecommendations",
        "dashboard.anomalyBreakdownTitle",
        "dashboard.anomalyChartsDesc",
        "dashboard.anomalyChartsTitle",
        "dashboard.anomalyCumulativeImpact",
        "dashboard.anomalySyncSuccess",
        "dashboard.autoAvailability",
        "dashboard.autoAvailabilityDesc",
        "dashboard.backup",
        "dashboard.backupTaskDesc",
        "dashboard.basedOnProfile",
        "dashboard.cachedData",
        "dashboard.completionDisabled",
        "dashboard.cumulAllTime",
        "dashboard.cumulVsPrev",
        "dashboard.dbWithoutRedisDesc",
        "dashboard.excludedLibrariesDesc",
        "dashboard.excludedLibrariesTitle",
        "dashboard.file",
        "dashboard.filterCategories",
        "dashboard.hoursAgo",
        "dashboard.lastError",
        "dashboard.lastSuccess",
        "dashboard.libraryRules",
        "dashboard.libraryRulesDesc",
        "dashboard.liveNow",
        "dashboard.logHealthDesc",
        "dashboard.manage",
        "dashboard.mediaSettings",
        "dashboard.mediaSettingsDesc",
        "dashboard.metadataAllGood",
        "dashboard.metadataAudit",
        "dashboard.metadataAuditDesc",
        "dashboard.minutesAgo",
        "dashboard.missingActors",
        "dashboard.missingGenres",
        "dashboard.missingResolution",
        "dashboard.mode",
        "dashboard.monitorStatusOk",
        "dashboard.multiServerComparator.desc",
        "dashboard.multiServerComparator.disabled",
        "dashboard.multiServerComparator.title",
        "dashboard.noExcludedLibraries",
        "dashboard.noOrphanPlaybacks",
        "dashboard.none",
        "dashboard.onTotalRegistered",
        "dashboard.openedOn",
        "dashboard.orphanItems",
        "dashboard.orphanPlaybacksDesc",
        "dashboard.orphanPlaybacksTitle",
        "dashboard.overviewDesc",
        "dashboard.playbackHistoryNote",
        "dashboard.processingStatusDesc",
        "dashboard.processingStatusTitle",
        "dashboard.recentClosuresDesc",
        "dashboard.recentClosuresTitle",
        "dashboard.redisOrphan",
        "dashboard.redisOrphanDesc",
        "dashboard.restore",
        "dashboard.rulesDesc",
        "dashboard.rulesTitle",
        "dashboard.scheduleSettingsDesc",
        "dashboard.schedulerBackups",
        "dashboard.sync",
        "dashboard.uncheckToHide",
        "dashboard.vsPrevPeriod",
        "dashboard.vsUsersOnPeriod",
        "dashboard.worldMap",
        "dashboard.worldMapDesc",
        "deepInsights.noDataSmall",
        "granular.durationByLibrary",
        "granular.durationByLibraryDesc",
        "granular.playsByLibrary",
        "granular.playsByLibraryDesc",
        "hardware.ram",
        "killStream.confirm",
        "liveStreams.description",
        "logs.activeFilter",
        "logs.audioFilter",
        "logs.booksFilter",
        "logs.clientFilter",
        "logs.dateFrom",
        "logs.dateTo",
        "logs.episodeType",
        "logs.movieType",
        "logs.moviesFilter",
        "logs.musicFilter",
        "logs.musicType",
        "logs.removeFilter",
        "logs.searchFilters",
        "logs.searchFiltersDesc",
        "logs.seasonType",
        "logs.seriesFilter",
        "logs.smartIpBurstItem",
        "logs.smartIpBurstTag",
        "logs.smartNewCountryDesc",
        "logs.subtitleFilter",
        "logs.timeline.label.audio_change",
        "logs.timeline.label.default",
        "logs.timeline.label.pause",
        "logs.timeline.label.seek",
        "logs.timeline.label.stop",
        "logs.timeline.label.subtitle_change",
        "logs.timeline.legend.audio",
        "logs.timeline.legend.pause",
        "logs.timeline.legend.subtitles",
        "logs.timeline.noEvents",
        "logs.timeline.stop",
        "logs.timeline.title",
        "logs.timeline.toggle.30s",
        "logs.timeline.toggle.5s",
        "logs.timeline.toggle.exact",
        "logs.typeFilter",
        "media.albumBadge",
        "media.audioFormats",
        "media.audioFormatsDesc",
        "media.audioOtherLabel",
        "media.availableContent",
        "media.flacLabel",
        "media.mp3Label",
        "media.noMedia",
        "media.seriesBadge",
        "media.sortBy",
        "media.sortPlayMode",
        "media.sortPopularity",
        "media.sortWatchTime",
        "media.timeDays",
        "media.title",
        "media.topDirectors",
        "mediaProfile.dropoff",
        "mediaProfile.dropoff0",
        "mediaProfile.dropoff1",
        "mediaProfile.dropoff2",
        "mediaProfile.dropoff3",
        "mediaProfile.dropoff4",
        "mediaProfile.dropoff5",
        "mediaProfile.dropoff6",
        "mediaProfile.dropoff7",
        "mediaProfile.dropoff8",
        "mediaProfile.dropoff9",
        "mediaProfile.episodes",
        "mediaProfile.markerCreditsStart",
        "mediaProfile.markerCustom",
        "mediaProfile.markerIntroEnd",
        "mediaProfile.markerIntroStart",
        "mediaProfile.seasons",
        "mediaProfile.sessionsTotal",
        "mediaProfile.stoppedAt",
        "mediaProfile.timeline.label.audio_change",
        "mediaProfile.timeline.label.pause",
        "mediaProfile.timeline.label.stop",
        "mediaProfile.timeline.label.subtitle_change",
        "mediaProfile.timeline_audio_change",
        "mediaProfile.timeline_pause",
        "mediaProfile.timeline_stop",
        "mediaProfile.timeline_subtitle_change",
        "mediaProfile.tracks",
        "mediaProfile.viewAlbum",
        "mediaProfile.viewSeries",
        "mediaProfile.viewers",
        "nav.cleanup",
        "nav.dashboard"
      ]
    }
  }
}